{"entries": [{"a": "woolf", "y": 1935, "m": 11, "d": 27, "place": "52 Tavistock Square, London", "lat": 51.5256, "lng": -0.1272, "text": "Too many specimen days—so I can't write. Yet, heaven help me, have a feeling that I've reached the no man's land that I'm after; and can pass from outer to inner and inhabit eternity. A queer very happy free feeling, such as I've not had at the finish of any other book. And this too is a prodigious long one. So what does it mean? Another balk this morning; can't get the start off of the last chapter right. What's wrong I don't know. But I needn't hurry. And the main thing is to let ideas blow easily; and come softly pouring. And not to be too emphatic. Of course to step straight into the middle of a new character is difficult: North: and I'm a little exacerbated; meant to have a quiet week, and here's Nelly C. and Nan Hudson both asking to come; and will I ring up; and Nan has a Turkish friend. But I will not be rushed. No.", "delta": 1}, {"a": "kafka", "y": 1911, "m": 11, "d": 26, "place": "Old Town, Prague", "lat": 50.0875, "lng": 14.4213, "text": "Sun. R. & S. with Max in the morning & afternoon until 5. Then to A. M. Pachinger. Collector from Linz, recommended by Kubin, 50 years old, huge, with tower-like movements, when he is silent for some time one bows one’s head, for he is entirely silent, whereas when speaking he does not entirely speak, his life consists of collecting and copulating. Collecting: He began\n\n with a collection of postage stamps, then moved on to graphic art, then collected everything, then saw the uselessness of this collection that would never be rounded off and limited himself to amulets, later to pilgrimage medals and pilgrimage leaflets from Lower Austria and South Bavaria. These are m. and l. that are reissued separately for each pilgrimage, are mostly worthless in their material and also artistically, but often contain pleasing depictions. He now also began to publish industriously on them, and indeed for the first time on this subject, for the systematization of which he first established the points of view. Naturally, the previous collectors of these things, who had neglected to publish, were indignant, but then had to resign themselves to it. Now he’s a recognized expert on these pilgrimage medals, from all over come requests for identification and appraisal of these medals, his voice carries weight. Moreover, he collects everything else too, his pride is a chastity belt (scapular?), which together with all his amulets was exhibited at the Dresden Hygiene Exhibition. (He was just there and had everything packed for transport.) Then a beautiful knight’s sword of a Falkensteiner. His relationship to art has a bad clarity attainable only through collecting. From the coffeehouse in the Hotel Graf he leads us up to his overheated room, sits down on the bed, we on 2 chairs around him, so that we form a quiet assembly. His first question “Are you collectors?” “No only poor enthusiasts.” “That doesn’t matter.” He pulls out his portfolio and fairly pelts us with bookplates, his own and others’, mixed in with a prospectus for his next book “Zauberei und Aberglaube im Steinreich.” He has already written a great deal, especially on “motherhood in art,” he considers the pregnant body the most beautiful, for him it’s also the most pleasant to screw. He has written about amulets too. He was also in the employ of the Vienna Court Museums, was in charge of excavations in Braila at the mouth of the Danube, invented a process named after him for binding excavated vases, is a 13fold member of learned societies and museums, his collection is bequeathed to the Germanic Museum in Nuremberg, he often sits at his desk at night until 1 or 2 o’clock and again at 8 in the morning. We have to write something in a female friend’s album that he has taken with him on the trip to fill up. Those who produce things themselves come first. Max inscribes a complicated verse, which Hr. P. tries to translate with the saying “After a storm comes a calm.” Beforehand he read it aloud with a wooden voice. I write:\n\n Little soul\n\n you leap in dance etc.\n\n he again reads aloud,\n\n I help, finally he says: “A Persian rhythm? What’s that called again? Ghazal? Right?” We can’t agree with that and can’t guess what he means either. Finally he quotes a ritornello by Rückert. Well then he meant ritornello. It’s not that either, though. All right, but it has a certain melodiousness. While leaving he throws apart the bed so that it fully adjusts to the warmth of the room, he also gives instructions for further heating.—He’s a friend of Halbe. He would like to talk about him. We’d much rather talk about Blei. But there’s not much to say about him, he’s disdained in the Munich literary societies because of lit. obscenities, he’s divorced from his wife, who as a dentist had a well-visited studio and supported him, his daughter 16 years old blond with blue eyes is the wildest girl in Munich. In Sternheim’s “Hose”—Pachinger was with Halbe in the theater—Blei played an aging bon vivant. When Pachinger met him the next day, he said “Herr Dr., yesterday you played Dr. Blei.” How so? how so? he said in embarrassment, but I played so-and-so.”—Kubin’s married life is bad. His wife is a morphinist. P. is convinced that Kubin is one too. One need only observe him when from the greatest liveliness he suddenly declines with sharp nose and hanging cheeks, must be woken, rouses himself to find his way back into the conversation, after an interval grows quiet again, which is then repeated at ever shorter intervals. He is also often at a loss for words.—On women: The stories about his potency make one think about how he must slowly stuff his large member into the women. His trick in earlier days was to exhaust women until they couldn’t go on. Then they were without a soul, animals. Yes this submissiveness I can imagine. He loves Rubens women as he says, but means those with large breasts bulging on top and flat and hanging baggily below. He explains this preference by saying that his first love was such a woman, a friend of his mother and mother of a schoolmate"}, {"a": "frank", "y": 1943, "m": 11, "d": 27, "place": "The Secret Annex, Prinsengracht 263, Amsterdam", "lat": 52.3752, "lng": 4.884, "text": "Dearest Kitty,\n\nLast night, just as I was falling asleep, Hanneli suddenly appeared before me.\n\nI saw her there, dressed in rags, her face thin and worn. She looked at me with such sadness and reproach in her enormous eyes that I could read the message in them: “Oh, Anne, why have you deserted me? Help me, help me, rescue me from this hell!”\n\nAnd I can’t help her. I can only stand by and watch while other people suffer and die. All I can do is pray to God to bring her back to us. I saw Hanneli, and no one else, and I understood why. I misjudged her, wasn’t mature enough to understand how difficult it was for her. She was devoted to her girlfriend, and it must have seemed as though I were trying to take her away. The poor thing, she must have felt awful! I know, because I recognize the feeling in myself! I had an occasional flash of understanding, but then got selfishly wrapped up again in my own problems and pleasures.\n\nIt was mean of me to treat her that way, and now she was looking at me, oh so helplessly, with her pale face and beseeching eyes. If only I could help her! Dear God, I have everything I could wish for, while fate has her in its deadly clutches. She was as devout as I am, maybe even more so, and she too wanted to do what was right. But then why have I been chosen to live, while she’s probably going to die? What’s the difference between us? Why are we now so far apart?\n\nTo be honest, I hadn’t thought of her for months—no, for at least a year. I hadn’t forgotten her entirely, and yet it wasn’t until I saw her before me that I thought of all her suffering.\n\nOh, Hanneli, I hope that if you live to the end of the war and return to us, I’ll be able to take you in and make up for the wrong I’ve done you.\n\nBut even if I were ever in a position to help, she wouldn’t need it more than she does now. I wonder if she ever thinks of me, and what she’s feeling?\n\nMerciful God, comfort her, so that at least she won’t be alone. Oh, if only You could tell her I’m thinking of her with compassion and love, it might help her go on.\n\nI’ve got to stop dwelling on this. It won’t get me anywhere. I keep seeing her enormous eyes, and they haunt me. Does Hanneli really and truly believe in God, or has religion merely been foisted upon her? I don’t even know that. I never took the trouble to ask.\n\nHanneli, Hanneli, if only I could take you away, if only I could share everything I have with you. It’s too late. I can’t help, or undo the wrong I’ve done. But I’ll never forget her again and I’ll always pray for her!\n\nYours, Anne", "delta": 1}, {"a": "pepys", "y": 1660, "m": 11, "d": 26, "place": "Seething Lane, City of London", "lat": 51.5104, "lng": -0.0796, "text": "(Office day). To it all the morning, and dined at home where my\nfather come and dined with me, who seems to take much pleasure to have\na son that is neat in his house. I being now making my new door into the\nentry, which he do please himself much with. After dinner to the office\nagain, and there till night. And that being done the Comptroller and\nI to the Mitre to a glass of wine, when we fell into a discourse of\npoetry, and he did repeat some verses of his own making which were very\ngood. Home, there hear that my Lady Batten had given my wife a visit\n(the first that ever she made her), which pleased me exceedingly. So\nafter supper to bed."}, {"a": "pepys", "y": 1662, "m": 11, "d": 26, "place": "Seething Lane, City of London", "lat": 51.5104, "lng": -0.0796, "text": "In the morning to the Temple to my cozen Roger, who now desires\nthat I would excuse him from arbitrating, he not being able to stand for\nme as he would do, without appearing too high against my uncle Thomas,\nwhich will raise his clamour. With this I am very well pleased, for\nI did desire it, and so I shall choose other counsel. Thence home,\nhe being busy that I could not speak more with him. All day long till\ntwelve o’clock at night getting my house in order, my wife putting up\nthe red hangings and bed in her woman’s chamber, and I my books and all\nother matters in my chamber and study, which is now very pretty. So to\nbed."}, {"a": "pepys", "y": 1663, "m": 11, "d": 26, "place": "Seething Lane, City of London", "lat": 51.5104, "lng": -0.0796, "text": "Up and to the office, where we sat all the morning, and at noon\nI to the ‘Change, and there met with Mr. Cutler the merchant, who would\nneeds have me home to his house by the Dutch Church, and there in an old\nbut good house, with his wife and mother, a couple of plain old women,\nI dined a good plain dinner, and his discourse after dinner with me upon\nmatters of the navy victualling very good and worth my hearing, and so\nhome to my office in the afternoon with my mind full of business, and\nthere at it late, and so home to supper to my poor wife, and to bed,\nmyself being in a little pain..... by a stroke.... in pulling up my\nbreeches yesterday over eagerly, but I will lay nothing to it till I see\nwhether it will cease of itself or no. The plague, it seems, grows more\nand more at Amsterdam; and we are going upon making of all ships coming\nfrom thence and Hambrough, or any other infected places, to perform\ntheir Quarantine (for thirty days as Sir Rd. Browne expressed it in the\norder of the Council, contrary to the import of the word, though in the\ngeneral acceptation it signifies now the thing, not the time spent in\ndoing it) in Holehaven, a thing never done by us before."}, {"a": "pepys", "y": 1664, "m": 11, "d": 26, "place": "Seething Lane, City of London", "lat": 51.5104, "lng": -0.0796, "text": "Up and to the office, where busy all the morning. Home a while to\ndinner and then to the office, where very late busy till quite weary,\nbut contented well with my dispatch of business, and so home to supper\nand to bed."}, {"a": "pepys", "y": 1665, "m": 11, "d": 26, "place": "Seething Lane, City of London", "lat": 51.5104, "lng": -0.0796, "text": "(Lord’s day). Up, though very late abed, yet before day to dress\nmyself to go toward Erith, which I would do by land, it being a horrible\ncold frost to go by water: so borrowed two horses of Mr. Howell and his\nfriend, and with much ado set out, after my horses being frosted\n\n [Frosting means, having the horses’ shoes turned up by the smith.]\n\n(which I know not what it means to this day), and my boy having lost one\nof my spurs and stockings, carrying them to the smith’s; but I borrowed\na stocking, and so got up, and Mr. Tooker with me, and rode to Erith,\nand there on board my Lord Bruncker, met Sir W. Warren upon his\nbusiness, among others, and did a great deale, Sir J. Minnes, as God\nwould have it, not being there to hinder us with his impertinences.\nBusiness done, we to dinner very merry, there being there Sir Edmund\nPooly, a very worthy gentleman. They are now come to the copper boxes\nin the prizes, and hope to have ended all this weeke. After dinner took\nleave, and on shore to Madam Williams, to give her an account of my\nLord’s letter to me about Howe, who he has clapped by the heels on\nsuspicion of having the jewells, and she did give me my Lord Bruncker’s\nexamination of the fellow, that declares his having them; and so away,\nSir W. Warren riding with me, and the way being very bad, that is,\nhard and slippery by reason of the frost, so we could not come to past\nWoolwich till night. However, having a great mind to have gone to the\nDuke of Albemarle, I endeavoured to have gone farther, but the night\ncome on and no going, so I ‘light and sent my horse by Tooker, and\nreturned on foot to my wife at Woolwich, where I found, as I had\ndirected, a good dinner to be made against to-morrow, and invited guests\nin the yarde, meaning to be merry, in order to her taking leave, for\nshe intends to come in a day or two to me for altogether. But here, they\ntell me, one of the houses behind them is infected, and I was fain to\nstand there a great while, to have their back-door opened, but they\ncould not, having locked them fast, against any passing through, so was\nforced to pass by them again, close to their sicke beds, which they were\nremoving out of the house, which troubled me; so I made them uninvite\ntheir guests, and to resolve of coming all away to me to-morrow, and I\nwalked with a lanthorne, weary as I was, to Greenwich; but it was a fine\nwalke, it being a hard frost, and so to Captain Cocke’s, but he I found\nhad sent for me to come to him to Mrs. Penington’s, and there I went,\nand we were very merry, and supped, and Cocke being sleepy he went away\nbetimes. I stayed alone talking and playing with her till past midnight,\nshe suffering me whatever ‘ego voulais avec ses mamilles.... Much\npleased with her company we parted, and I home to bed at past one, all\npeople being in bed thinking I would have staid out of town all night."}, {"a": "pepys", "y": 1666, "m": 11, "d": 26, "place": "Seething Lane, City of London", "lat": 51.5104, "lng": -0.0796, "text": "Up, and to my chamber to do some business. Then to speak with\nseveral people, among others with Mrs. Burroughs, whom I appointed to\nmeet me at the New Exchange in the afternoon. I by water to Westminster,\nand there to enquire after my tallies, which I shall get this week.\nThence to the Swan, having sent for some burnt claret, and there by\nand by comes Doll Lane, and she and I sat and drank and talked a great\nwhile, among other things about her sister’s being brought to bed, and\nI to be godfather to the girle. I did tumble Doll, and do almost what\nI would with her, and so parted, and I took coach, and to the New\nExchange, buying a neat’s tongue by the way, thinking to eat it out of\ntown, but there I find Burroughs in company of an old woman, an aunt of\nhers, whom she could not leave for half an hour. So after buying a few\nbaubles to while away time, I down to Westminster, and there into the\nHouse of Parliament, where, at a great Committee, I did hear, as long\nas I would, the great case against my Lord Mordaunt, for some arbitrary\nproceedings of his against one Taylor, whom he imprisoned, and did all\nthe violence to imaginable, only to get him to give way to his abusing\nhis daughter. Here was Mr. Sawyer, my old chamber-fellow, a counsel\nagainst my Lord; and I am glad to see him in so good play. Here I met,\nbefore the committee sat, with my cozen Roger Pepys, the first time I\nhave spoke with him this parliament. He hath promised to come, and bring\nMadam Turner with him, who is come to towne to see the City, but hath\nlost all her goods of all kinds in Salisbury Court, Sir William Turner\nhaving not endeavoured, in her absence, to save one penny, to dine with\nme on Friday next, of which I am glad. Roger bids me to help him to some\ngood rich widow; for he is resolved to go, and retire wholly, into\nthe country; for, he says, he is confident we shall be all ruined very\nspeedily, by what he sees in the State, and I am much in his mind.\nHaving staid as long as I thought fit for meeting of Burroughs, I away\nand to the ‘Change again, but there I do not find her now, I having\nstaid too long at the House, and therefore very hungry, having eat\nnothing to-day. Home, and there to eat presently, and then to the office\na little, and to Sir W. Batten, where Sir J. Minnes and Captain Cocke\nwas; but no newes from the North at all to-day; and the newes-book makes\nthe business nothing, but that they are all dispersed. I pray God it may\nprove so. So home, and, after a little, to my chamber to bed."}, {"a": "pepys", "y": 1667, "m": 11, "d": 26, "place": "Seething Lane, City of London", "lat": 51.5104, "lng": -0.0796, "text": "Up, all the morning at the office, and then home to dinner, where\ndined Mr. Clerke, solicitor, with me, to discourse about my Tangier\naccounts, which I would fain make up, but I have not time. After dinner,\nby coach as far as the Temple, and there saw a new book, in folio, of\nall that suffered for the King in the late times, which I will buy,\nit seems well writ, and then back to the Old Exchange, and there at my\ngoldsmith’s bought a basin for my wife to give the Parson’s child, to\nwhich the other day she was godmother. It cost me; L10 14s. besides\ngraving, which I do with the cypher of the name, Daniel Mills, and so\nhome to the office, and then home to supper and hear my wife read, and\nthen to bed. This afternoon, after dinner, come to me Mr. Warren, and\nthere did tell me that he come to pay his debt to me for the kindness I\ndid him in getting his last ship out, which I must also remember was\na service to the King, though I did not tell him so, as appeared by my\nadvising with the board, and there writing to Sir W. Coventry to get the\npass for the ship to go for it to Genoa. Now that which he had promised\nme for the courtesy was I take it 100 pieces or more, I think more, and\nalso for the former courtesy I had done for the getting of his first\nship out for this hemp he did promise me a consideration upon the return\nof the goods, but I never did to this day demand any thing of him, only\nabout a month ago he told me that now his ship was come, and he would\ncome out of my debt, but told me that whereas he did expect to have had\nsome profit by the voyage, it had proved of loss to him, by the loss of\nsome ships, or some accidents, I know not what, and so that he was not\nable to do what he intended, but told me that he would present me with\nsixty pieces in gold. I told him I would demand nothing of his promises,\nthough they were much greater, nor would have thus much, but if he could\nafford to give me but fifty pieces, it should suffice me. So now he\nbrought something in a paper, which since proves to be fifty pieces. But\nbefore I would take them I told him that I did not insist on anything,\nand therefore prayed him to consult his ability before he did part with\nthem: and so I refused them once or twice till he did the third time\noffer them, and then I took them, he saying that he would present me\nwith as many more if I would undertake to get him L500 paid on his\nbills. I told him I would by no means have any promise of the kind, nor\nwould have any kindness from him for any such service, but that I should\ndo my utmost for nothing to do him that justice, and would endeavour to\ndo what I could for him, and so we parted, he owning himself mightily\nengaged to me for my kind usage of him in accepting of so small a matter\nin satisfaction of all that he owed me; which I enter at large for my\njustification if anything of this should be hereafter enquired after.\nThis evening also comes to me to my closet at the Office Sir John\nChichly, of his own accord, to tell me what he shall answer to the\nCommittee, when, as he expects, he shall be examined about my Lord\nSandwich; which is so little as will not hurt my Lord at all, I know. He\ndo profess great generousness towards my Lord, and that this jealousy of\nmy Lord’s of him is without ground, but do mightily inveigh against Sir\nRoger Cuttance, and would never have my Lord to carry him to sea again,\nas being a man that hath done my Lord more hurt than ever he can repair\nby his ill advice, and disobliging every body. He will by no means seem\nto crouch to my Lord, but says that he hath as good blood in his veins\nas any man, though not so good a title, but that he will do nothing to\nwrong or prejudice my Lord, and I hope he will not, nor I believe can;\nbut he tells me that Sir E. Spragg and Utber are the men that have done\nmy Lord the most wrong, and did bespatter him the most at Oxford, and\nthat my Lord was misled to believe that all that was there said was his,\nwhich indeed it was not, and says that he did at that time complain\nto his father of this his misfortune. This I confess is strange to me\ntouching these two men, but yet it may well enough as the world goes,\nthough I wonder I confess at the latter of the two, who always professes\ngreat love to my Lord. Sir Roger Cuttance was with me in the morning,\nand there gives me an account so clear about Bergen and the other\nbusiness against my Lord, as I do not see what can be laid to my Lord in\neither, and tells me that Pen, however he now dissembles it, did on the\nquarter deck of my Lord’s ship, after he come on board, when my Lord\ndid fire a gun for the ships to leave pursuing the enemy, Pen did say,\nbefore a great many, several times, that his heart did leap in his belly\nfor joy when he heard the gun, and that it was the best thing that could\nbe done for securing the fleet. He tells me also that Pen was the first\nthat did move and persuade my Lord to the breaking bulke, as a thing\nthat was now the time to do right to the commanders of the great ships,\nwho had no opportunity of getting anything by prizes, now his Lordship\nmight distribute to everyone something, and he himself did write down\nbefore my Lord the proportions for each man. This I am glad of, though\nit may be this dissembling fellow may, twenty to one, deny it."}, {"a": "pepys", "y": 1668, "m": 11, "d": 26, "place": "Seething Lane, City of London", "lat": 51.5104, "lng": -0.0796, "text": "Up, and at the Office all the morning, where I was to have\ndelivered the Duke of York’s letter of advice to the Board, in answer\nto our several answers to his great letter; but Lord Brouncker not being\nthere, and doubtful to deliver it before the new Treasurers, I forbore\nit to next sitting. So home at noon to dinner, where I find Mr. Pierce\nand his wife but I was forced to shew very little pleasure in her being\nthere because of my vow to my wife; and therefore was glad of a very bad\noccasion for my being really troubled, which is, at W. Hewer’s losing\nof a tally of L1000, which I sent him this day to receive of the\nCommissioners of Excise. So that though I hope at the worst I shall be\nable to get another, yet I made use of this to get away as soon as I had\ndined, and therefore out with him to the Excise Office to make a stop of\nits payment, and so away to the coachmaker’s and several other places,\nand so away home, and there to my business at the office, and thence\nhome, and there my wife to read to me, and W. Hewer to set some matters\nof accounts right at my chamber, to bed."}, {"a": "eno", "y": 1995, "m": 11, "d": 26, "place": "His studio, west London", "lat": 51.516, "lng": -0.205, "text": "Bill’s 80th birthday party, beautifully organized by Anthea, at Cliveden. Odd feeling, being at a clan meeting of that sort, where people who haven’t seen each other for decades come together again, or where relatives who’ve never met do so for the first time. A slight sadness too, as many of the older people said goodbye to each other. I thought, ‘They must realize they’ll probably never meet again’, and then I thought this must have been a much more common experience in earlier times – people saying goodbye for good. What must it have been like, your young son leaving to seek his fortune in Australia?\n\nI suppose we had some of that feeling when Rita left for Seattle. I think I felt I would probably never see her again. What a sad, brave ride that was, from Woodbridge to Heathrow airport in Dad’s car, all three of us chattering too brightly to conceal our heavy hearts. I never considered before how heartbreaking that must have been for Dad, who loved Rita – his stepdaughter – so much, and for Mum, who didn’t even make the journey, because Arlette had just been born – another daughter appearing as one left. That was in 1961."}, {"a": "warhol", "y": 1976, "m": 11, "d": 26, "place": "Chadds Ford, Pennsylvania", "lat": 39.8718, "lng": -75.5919, "text": "Went on a tour of Winterthur in the morning (tickets $24, books $59). Then Phyllis Wyeth got the buggy together, we had an all-American breakfast, fed Archie and Amos [see Introduction], then we went out for a ride. We went across the Brandywine River in it, it wasn’t so deep.\n\nJed went to meet Vincent [see introduction] and Shelly and Ronnie [see Introduction] and Gigi at the train station. Went with Jamie to the Brandywine Museum and we were photographed and had a press conference. Went back to Jamie and Phyllis’s and there were cocktails. Mrs. Bartow who I bought the East 66th Street house from was there and she asked when I was going to sandblast it and why was I never home because it always looked dark. Carter Brown was there and Jane Holzer with Bob Denison.\n\nRode to the museum. I introduced Gigi as “George”—I’d told this guy she was a drag queen and he didn’t know I was kidding, he got excited—and then she said, “No, it’s Georgette,” which coincidentally is her real name—I didn’t know it. So everything was coming out right—I mean it was just what a drag queen would say, so that was funny. And the guy really liked her and she didn’t have a clue it was because he thought she was a boy."}, {"a": "warhol", "y": 1978, "m": 11, "d": 26, "place": "57 East 66th Street, New York", "lat": 40.7677, "lng": -73.9648, "text": "I called Bob and he was grouchy, he said he couldn’t talk because he was writing his “Out” column. I don’t know what he’s so grouchy for, it’s the only writing he does all month.\n\nI went to church, it was so beautiful and cold out. Then I worked. I drew earths and moons and watched TV."}, {"a": "warhol", "y": 1981, "m": 11, "d": 26, "place": "57 East 66th Street, New York", "lat": 40.7677, "lng": -73.9648, "text": "Well, got up, depressed, had a lonely day. No calls from Jon. Ate some Bill Blass chocolates. Ate leftover turkey. I called Halston but got the wrong number. Finally at a quarter to 6:00 I walked to Liza’s. It was really homey. It was Liza and Mark Gero and his mother and father and uncle and three brothers and a Polish girl and Halston and Victor Hugo.\n\nThe dinner was in the hallway with all my portraits of Liza. It looked really beautiful. And I said to Mark, “I think I’ve seen this apartment in some magazines,” and he said, “Yeah, Batman Comics.” He was funny. And he’s the best-looking of the brothers. Liza got the cream. And I figured out that the mother is, I think, Polish, so that’s why they have that big Polish-Italian look. One of the brothers is a teacher at Harvard.\n\nAnd I was really crazy, I was nutty, plus I was drinking good red wine from the Napa Valley. I said, “So now that we’ve got the whole family here, which one is the fairy?” And the Harvard one did a fairy voice and said, “Mommy, which one’s the fairy?” It was funny. The mother is beautiful.\n\nMartha Graham was there with her boyfriend Ron Protas and his boyfriend."}, {"a": "warhol", "y": 1982, "m": 11, "d": 26, "place": "57 East 66th Street, New York", "lat": 40.7677, "lng": -73.9648, "text": "Found out that after I left Halston’s, Rusty discovered a fire that’d started in a fireplace and gone to a Marisol sculpture and into a closet, and if Rusty hadn’t noticed it, Halston’s would have burned.\n\nI’m giving everyone framed underwear for Christmas. Went up to 86th Street and then down (cabs $5, $4).\n\nJon called, said he was back in town."}, {"a": "warhol", "y": 1984, "m": 11, "d": 26, "place": "57 East 66th Street, New York", "lat": 40.7677, "lng": -73.9648, "text": "Dr. Linda Li can’t find out what’s causing my allergies. She said my spleen was traumatized fifteen years ago.\n\nHad a talk with the Harper & Row editor, Craig Nelson, and had to tell him what I thought of what he’d written for the America book: He can’t write."}, {"a": "luxun", "y": 1912, "m": 11, "d": 26, "place": "绍兴会馆，北京宣武门外", "lat": 39.8934, "lng": 116.3745, "text": "上午寄二弟信。晚收二十一日《天觉报》一分。"}, {"a": "luxun", "y": 1914, "m": 11, "d": 26, "place": "绍兴会馆，北京宣武门外", "lat": 39.8934, "lng": 116.3745, "text": "曇。上午寄二弟信（七十六）。答陶念欽先生信。得二弟所寄書籍兩束，計《小學答問》二部二冊，《文史通義》一部六午後至東交民巷寄相摸屋書店信，代子英匯書款日金三十圓，需中銀至四十元。下午得婦來書，二十二日從丁家弄朱宅發，頗謬。晚童亞鎮來，言已匯款百元於家，因即付之，复除下前所借之三十元，與之七十。"}, {"a": "luxun", "y": 1915, "m": 11, "d": 26, "place": "绍兴会馆，北京宣武门外", "lat": 39.8934, "lng": 116.3745, "text": "晴。上午寄二弟信(八十八)。收本月奉泉二百八十元。午後同陳師曾至小市。晚許季上來。夜大風。"}, {"a": "luxun", "y": 1916, "m": 11, "d": 26, "place": "绍兴会馆，北京宣武门外", "lat": 39.8934, "lng": 116.3745, "text": "昙，风。星期休息。上午得二弟信，廿二日发(102)。得和孙信，廿一日发。午后往留黎厂买石刻拓本，凡安阳残石四种，阙一枚，今共五枚，四元；足拓《禅国山碑》一枚，四元；隋石经残石一枚，《段怀穆造塔残石》一枚，《六十人造象》一枚，各一元；杂造象四枚，五角；《李崧残石》一枚，五角；《襄阳张氏墓志》十种十六枚，一元。下午季自求、卢闰州来，未遇。晚寄二弟碑目一卷。"}, {"a": "luxun", "y": 1917, "m": 11, "d": 26, "place": "绍兴会馆，北京宣武门外", "lat": 39.8934, "lng": 116.3745, "text": "雨。上午寄季市《饮流斋说瓷》二册，还《少年兵团》一册。下午收本月奉泉三百。振直隶水灾十一元。晚得李遐卿信并帖签四枚。得伯㧑叔信，二十二日南京发。"}, {"a": "luxun", "y": 1918, "m": 11, "d": 26, "place": "绍兴会馆，北京宣武门外", "lat": 39.8934, "lng": 116.3745, "text": "晴。下午收本月奉泉三百。捐于欧战协济会卅。"}, {"a": "luxun", "y": 1919, "m": 11, "d": 26, "place": "绍兴会馆，北京宣武门外", "lat": 39.8934, "lng": 116.3745, "text": "昙。上午收本月奉泉之半，计券一百五十。午后寄罗志希信。上书请归省。付木工泉五十。重校《青年之梦》第一幕讫。"}, {"a": "luxun", "y": 1920, "m": 11, "d": 26, "place": "八道湾十一号，北京", "lat": 39.9391, "lng": 116.3663, "text": "晴。病，休息。夜服规那十厘。"}, {"a": "luxun", "y": 1923, "m": 11, "d": 26, "place": "阜成门内西三条，北京", "lat": 39.9265, "lng": 116.3475, "text": "晴。午后往世界语校讲。下午紫佩来，不直，留笺而去。"}, {"a": "luxun", "y": 1924, "m": 11, "d": 26, "place": "阜成门内西三条，北京", "lat": 39.9265, "lng": 116.3475, "text": "晴。上午得玄同信。得子佩信。得李庸倩信片，十四日上海发。下午复玄同信。复子佩信。晚H君来。收《东方杂志》一本。得新潮社信。"}, {"a": "luxun", "y": 1925, "m": 11, "d": 26, "place": "阜成门内西三条，北京", "lat": 39.9265, "lng": 116.3475, "text": "晴。上午得向培良、黄鹏基信。午后往黎明讲。得韦素园信。下午矛尘来。寄妇女周刊社信并稿。晚子佩来。得衣萍信。得顾孟余信。"}, {"a": "luxun", "y": 1926, "m": 11, "d": 26, "place": "厦门大学", "lat": 24.4368, "lng": 118.0973, "text": "晴，大风。下午寄景宋信。林河清来。晚蒋希曾来。夜观电影。"}, {"a": "luxun", "y": 1927, "m": 11, "d": 26, "place": "虹口，上海", "lat": 31.27, "lng": 121.4805, "text": "晴。下午小峰、衣萍、铁民来。绍原来。晚小峰邀往东亚食堂夜餐，同坐共六人。夜往内山书店买《マメリカ文学》一本，泉二元。托三弟往中国书店买石印本《承华事略》一部二本，一元。"}, {"a": "luxun", "y": 1928, "m": 11, "d": 26, "place": "虹口，上海", "lat": 31.27, "lng": 121.4805, "text": "晴。上午得语堂信。得矛尘信。下午吴敬夫及其友数人来。夜得小峰信及《而已集》、《语丝》。得李荐侬信。得石民信。"}, {"a": "luxun", "y": 1929, "m": 11, "d": 26, "place": "虹口，上海", "lat": 31.27, "lng": 121.4805, "text": "晴。上午同广平携海婴往福民医院诊察，体重计三千八百七十格伦。下午往小林制版所取铜版。得王余杞信并稿。达夫来。寄心梅叔泉五十。寄季志仁信并泉五百法郎。晚许叔和及夫人、孩子来。"}, {"a": "luxun", "y": 1930, "m": 11, "d": 26, "place": "虹口，上海", "lat": 31.27, "lng": 121.4805, "text": "晴。上午往平井博士寓为石民作翻译，并自乞诊。下午往街买药。晚三弟来，留之晚酌。收东方杂志社稿费三十。"}, {"a": "luxun", "y": 1931, "m": 11, "d": 26, "place": "虹口，上海", "lat": 31.27, "lng": 121.4805, "text": "昙。下午汉嘉堡[堡嘉]夫人来借版画。《毁灭》制本成。"}, {"a": "jixianlin", "y": 1932, "m": 11, "d": 26, "place": "清华园，北平", "lat": 40.0106, "lng": 116.3331, "text": "今天开始作Galsworthy的生平和著作（二十五日作的），过午作戏剧家的Galsworthy和为长篇小说家的 Galsworthy。不过，这所谓作，并不是定稿，不过把书上的材料摘下来。至于前后次序，那是抄的时候的工夫了。\n\n晚上头颇痛，需要休息。民众学校送来电影票，去看电影以苏困。片子是《招请国王》，一塌糊涂，坏极了。\n\n电影完后，点蜡，作为短篇小说家、小品文家和诗人的Galsworthy和一篇附尾。睡觉时下一点。\n\n二十七日 星期日\n\n昨天虽然睡得晚，但今天一早就醒了——Galsworthy把我催醒的。\n\n我开始抄，这抄的工夫也真真要命。又要顾到是否前后重复或冲突，又要顾到文字。有时因为一两行费半点钟的工夫。头也因而更痛了。\n\n过午仍继续抄，终于没抄完。"}, {"a": "jixianlin", "y": 1933, "m": 11, "d": 26, "place": "清华园，北平", "lat": 40.0106, "lng": 116.3331, "text": "虽然是星期，但却没能读多少书，因为自己觉得，星期日本来应该进城的，竟没进城。只读一点书，也就觉得比不读强多了。\n\n看老舍的《离婚》，很不坏，比《猫城记》强多了。\n\n几天来，老想到要写文章。根本没有文章而自己以为是个作家，不是很滑稽的事吗?"}, {"a": "hushi", "y": 1914, "m": 11, "d": 25, "place": "康乃尔大学，绮色佳（Ithaca）", "lat": 42.4534, "lng": -76.4735, "text": "四四、大同主义之先哲名言\n\nAristippus said that a wise man's country was the world.\n\n—Diogenes Laertius, Aristippus , Ⅷ\n\nDiogenes, when asked from what country he came, replied, \"I am a citizen of the world.\"\n\n——同上\n\nSocrates said he was not an Athenian or a Greek, but a citizen of the world.\n\n—Plutarch, On Banishment\n\nMy country is the world, and my religion is to do good.\n\n—Thomas Paine, Rights of Man, chap ．V\n\nMy country is the world；my countrymen are mankind.\n\n—Wm Lloyd Garrison (1805—1879), Prospectus of the Public Liberator\n\n（1830）\n\n〔中译 〕\n\n亚里斯提卜说过智者的祖国就是世界。\n\n——第欧根尼·拉尔修：《亚里斯提卜》第十三章\n\n当有人问及他是何国之人时，第欧根尼回答道：“我是世界之公民。”\n\n——第欧根尼·拉尔修：《亚里斯提卜》第十三章\n\n苏拉底说他既不是一个雅典人也不是一个希腊人，只不过是一个世界公民。\n\n——普卢塔：《流放论》\n\n我的祖国是世界，我的宗教是行善。\n\n——T·潘恩：《人类的权利》第五章\n\n世界是我的祖国，人类是我的同胞。\n\n——W. L. 加里森（1805—1879）《解放者简介》（1830）\n\n四五、“My country，right or wrong”之出处\n\n吾前所记“My country，right or wrong！”（吾国，是耶，非耶！）一语盖Stephen Decatur（1779—1820）之言。其全文如下：\n\n\"Our country! In her intercourse with foreign nations may she always be in the right; but our country, right or wrong.\"\n\n—Toast given at Norfolk, Apr. 1816.\n\n〔中译 〕\n\n吾国乎，吾愿其永永正直而是也，然曲耶，直耶，是耶，非耶，终为吾国耳。\n\n——致祝酒辞，1816年4月于诺福克\n\n此与下二则同意：\n\n（1）Be England what she will,\n\nWith all her faults she is my country still．\n\n—Charles Churchill (1731—1764): The Farewell\n\n（2）England，with all thy faults I love thee still,\n\nMy country!\n\n—Wm. Cowper (1731—1800) \"The Task\" Ⅱ\n\n〔中译 〕\n\n（1）不管如何，她终是英格兰，\n\n尽管一身错，她仍是我的祖国。\n\n——查尔斯·丘吉尔（1731—1764）：《惜别》\n\n（2）我的祖国！英格兰，不管你有何缺点，我仍深爱着你。\n\n——W. 库柏（1731—1800）：《使命》Ⅱ\n\n四六、犹太文豪Asher Ginzberg\n\n吾友薛尔勿曼（L. L. Silverman）博士以犹太文豪Asher Ginzberg（“Ahad Ha'Am”〔one of the people〕）所著文相假（“Selected Essays”：Philadelphia：The Jewish Publication Society of America，1912）。此君博学能文，爱其种人最切，著书甚富。其人通英德法诸国文，而誓不以他种文字著作，其书皆希伯来文也。贫甚而不欲以卖文为活，居伦敦卖花生果为生，人不知其为名闻天下之名士也，盖有其先哲斯平娜莎（Spinoza，亦犹太人）之遗风，二十世纪奇士之一也。此集乃其种人由希伯来文译为英文者。其文都佳，尤爱其Two Masters 一篇。", "delta": 1}, {"a": "hushi", "y": 1915, "m": 11, "d": 25, "place": "哥伦比亚大学，纽约", "lat": 40.8075, "lng": -73.9626, "text": "一、许肇南来书\n\n许肇南自南京（十月廿三日）来书：\n\n目下帝制运动极形活动。中华民国早变官国，其必有皇帝，宜也。时局危险，当局亦岂不知之？然爱国之心不敌其做皇帝与封侯拜相之瘾，故演成现时怪状。自我观之，招牌换后，一二在朝贤者必皆退隐。剥极之时，内乱且生。然能复兴否，殊未可必，以有日本乘我之危也。又值均势打破之时，国命如何，正不忍言。在理，以吾国现在人心社会，若不亡国，亦非天理。吾人一息尚存，亦努力造因而已。欲扬眉吐气，为强国之民，吾辈曾元庶得享此幸福。某为此言，非持悲观主义。某以为现在中国较前实有进步。特造孽太久，揆诸因果相寻之理，不易解脱耳。曾文正有言：“不问收获，且问耕耘。”某至今犹服膺此语。亦甚冀海外故人之“努力崇明德，随时爱景光”也。\n\n二、杨杏佛《遣兴》诗\n\n《季报》第二年一号有杏佛《遣兴》诗：\n\n黄叶舞秋风，白云自西去。落叶归深涧，云倦之何处？\n\n（适以为末二句如改“落叶下深涧，云倦归何处？”当更佳。）\n\n余极喜之，以为杏佛年来所作诗，当以此二十字为最佳。\n\n三、《晚邮报》论“将来之世界”\n\n十一月十日，纽约《晚邮报》有社论一篇，题曰《将来之世界》。其大意以为世界者，乃世界人之世界，不当由欧美两洲人独私有之。亚洲诸国为世界一部分，不宜歧视之。其最要之语为下录两节：\n\nThe state of mind against which the new spirit among the peoples in Asia protests is the one which sees the world as made up of two continents only, and which regards a world-settlement as any settlement that regulates matters in these two continents, with a minimum of cutting and trimming here and there in Africa and Asia to make the Western adjustment as smooth as may be. \"We shall not falter or pause,\" said Mr. Asquith yesterday, \"until we have secured for the smaller states of Europe their charter of independence, and for Europe itself final emancipation from a reign of force.\" But radical opinion in India fails to understand why a war fought in Asia as well as in Europe, and one in which the people of India are taking part, should leave Asia out of account in the settlement. There are Indian aspirations as well as Serb and Polish aspirations. Asia is part of the world. Unquestionably, the war will bring about a wider recognition of the true area of the globe, if only through the fact that it has brought together on the battlefield a more extraordinary mingling of races than the Roman armies ever witnessed—from America, from Africa, from Australia, and from Asia, as well as from Europe.\n\nIt is still true that when we speak of the world-war and of the world as it will look after the war, we think almost exclusively of the nations of the West. What will happen to seven million Belgians, what will happen to less than five million Serbs, is a more entrancing question than what the war will do for more than three hundred million people in India or nearly three hundred and fifty million in China. Where India and China are taken into account, they still figure as mere appendages to Western interests. Will Teuton or Allied influence in China be paramount after the war? How seriously are the German threats against British rule in India to be taken; in other words, will India belong to Great Britain or will it pass under Germanic influences? We admit that Asiatic problems have been brought into closer touch with Western problems, but when we speak of the great settlement after the war, the settlement of Asia hardly enters into the reckoning except as it may enter as an incidental facior in the rearrangement of affairs in Europe.\n\n〔中译 〕\n\n亚洲人持有一种精神，即反对这样一种心态：总以为世界只由两块大陆组成，总把世界之事务当作两个大陆之事务来处理；在处理非洲、亚洲之事务方面，只需作些最低限度之砍削、修补，使之尽可能适应西方之调整运作。阿斯奎斯先生说：“直到欧洲之小国家皆获得独立宪章，直到欧洲最终从强权统治下解放出来，我们才肯罢休，才肯撒手不管。”可是，印度之激进主义者却不明白，为什么在处理战争事务时，不论是亚洲之战争，还是欧洲之战争，甚至于是印度人也参与其中之战争，均把亚洲排除在外。塞尔维亚人有塞尔维亚人之志气；波兰人有波兰人之抱负；同样，印度人也有印度人之渴望。亚洲是世界之一分子。毫无疑问，这场世界战争将在全球范围内引起广泛之重视，我们只要看看下列事实即可明白：许多民族被卷入这场战争，在战场上兵戎相见，其数量之多，种类之杂远远超过古罗马军队所曾经历过的——这些民族有来自美洲的，来自非洲的，来自澳洲的，来自亚洲的，还有自然是来自欧洲的。\n\n当我们说到世界大战以及战争所波及到之世界时，我们也同样会将西方各国排除在外。七百万比利时人之命运，近五百万塞尔维亚人之命运，比起三亿多印度人或将近三亿五千万中国人之战争遭遇，将是一个更加令人出神之问题。凡涉及印度和中国事务，他们仍然只是作为西方利益之附加物来考虑。战后，条顿人 (1) 或协约国在中国之影响还很重要吗？德国反对英国统治印度之态度强烈吗？换言之，印度将属于大不列颠统辖呢？抑或还是在德国势力之庇护下生存呢？尽管我们承认，亚洲问题已与西方问题日益密切，休戚相关，但是，当我们言及战后事务之处理时，很难把亚洲事务纳入统盘考虑之中；除非在对欧洲事务作重新安排时，我们才将亚洲事务作为其附带之因素，而加以一并考虑。\n\n余与吾友郑莱及韦女士皆久持此意。今见此邦一最有势之日报创为此论，吾辈之表同意可知也。余连日极忙，然不忍终默，乃于百忙中作一书寄《晚邮报》（书载十一月廿三日报），引申其意。此等孤掌之鸣，明知其无益，而不忍不为也。", "delta": 1}, {"a": "einstein", "y": 1922, "m": 11, "d": 26, "place": "东京", "lat": 35.6762, "lng": 139.6503, "text": "插图13　在物理学家长冈半太郎东京的住所里的午餐菜单（承蒙普林斯顿大学图书馆惠允）。"}]}